specsanalyzer/__init__.py
specsanalyzer/config.py
specsanalyzer/convert.py
specsanalyzer/core.py
specsanalyzer/img_tools.py
specsanalyzer/io.py
specsanalyzer/logging.py
specsanalyzer/config/default.yaml
specsanalyzer/config/phoibos150.calib2d
specsanalyzer-1.2.0.dist-info/licenses/LICENSE
specsscan/__init__.py
specsscan/core.py
specsscan/helpers.py
specsscan/metadata.py
specsscan/config/NXmpes_arpes_config.json
specsscan/config/default.yaml
specsscan/config/example_config_FHI.yaml
specsanalyzer-1.2.0.dist-info/METADATA
specsanalyzer-1.2.0.dist-info/WHEEL
specsanalyzer-1.2.0.dist-info/top_level.txt
specsanalyzer-1.2.0.dist-info/RECORD
